wuff.pypy310-pp73-x86-linux-gnu.so
wuff-1.2.1.dist-info/WHEEL
wuff-1.2.1.dist-info/top_level.txt
wuff-1.2.1.dist-info/METADATA
wuff-1.2.1.dist-info/RECORD
