Metadata-Version: 2.4
Name: wuff
Version: 1.2.1
Summary: Analysis engine for WooWoo workspaces.
Author: Michal Janecek
Author-email: michal.janecek@gmail.com
Requires-Python: >=3.8
Provides-Extra: test
Requires-Dist: pytest>=6.0; extra == "test"
Dynamic: author
Dynamic: author-email
Dynamic: description
Dynamic: description-content-type
Dynamic: provides-extra
Dynamic: requires-python
Dynamic: summary
